monolg/__init__.py
monolg/_schemas.py
monolg/errors.py
monolg/mongo_log.py
monolg/utils.py
monolg-0.0.1.dist-info/LICENSE
monolg-0.0.1.dist-info/METADATA
monolg-0.0.1.dist-info/WHEEL
monolg-0.0.1.dist-info/top_level.txt
monolg-0.0.1.dist-info/RECORD
