Metadata-Version: 2.1
Name: monolg
Version: 0.0.1
Summary: Centralized logging for Python using MongoDB
Home-page: https://github.com/Mukhopadhyay/monolg
Author: Pranesh Mukhopadhyay
Author-email: praneshmukherjee7@gmail.com
Maintainer: Pranesh Mukhopadhyay
Maintainer-email: praneshmukherjee7@gmail.com
License: MIT license
Keywords: monolg
Platform: UNKNOWN
Classifier: Intended Audience :: Developers
Classifier: License :: OSI Approved :: MIT License
Classifier: Natural Language :: English
Classifier: Programming Language :: Python :: 3
Classifier: Programming Language :: Python :: 3.6
Classifier: Programming Language :: Python :: 3.7
Classifier: Programming Language :: Python :: 3.8
Requires-Python: >=3.6
Requires-Dist: colorama (==0.4.5)
Requires-Dist: dnspython (==2.2.1)
Requires-Dist: pymongo (==4.2.0)
